{
  "geografis": "RPL:1",
  "klasifikasi": "RPL:1",
  "android": "RPL:1",
  "game": "RPL:1",
  "informasi": "RPL:1",
  "putusan": "RPL:1",
  "knn": "RPL:1 KCV:1",
  "ahp": "RPL:1",
  "saw": "RPL:1",
  "naive": "RPL:1",
  "bayes": "RPL:1",
  "klastering": "RPL:1",
  "prediksi": "RPL:2",
  "c45": "RPL:2",
  "horspol": "RPL:1",
  "apriori": "RPL:2",
  "cart": "RPL:1",
  "ramal": "RPL:1",
  "clustering": "RPL:1",
  "mining": "RPL:1",
  "kelompok": "RPL:1",
  "werehouse": "RPL:1",
  "pendek": "RPL:1",
  "3d": "RPL:1",
  "2d": "RPL:1",
  "forcasting": "RPL:1",
  "exponential": "RPL:1",
  "cari": "RPL:2",
  "": "RPL:1 KCV:2",
  "linear": "RPL:1",
  "congruent": "RPL:2",
  "method": "RPL:1",
  "augmented": "RPL:1",
  "geographic": "RPL:1",
  "information": "RPL:1",
  "system": "RPL:1",
  "sentimen": "RPL:1",
  "integer": "RPL:1",
  "maps": "RPL:1",
  "dss": "RPL:1",
  "rekayasa": "RPL:1",
  "smarthome": "RPL:1",
  "kuis": "RPL:1",
  "raita": "RPL:1",
  "simple": "KCV:2 RPL:2",
  "multi": "RPL:1 KCV:1",
  "attribute": "RPL:1 KCV:1",
  "rating": "RPL:1 KCV:1",
  "technique": "RPL:1 KCV:1",
  "electre": "RPL:1",
  "promethee": "RPL:1",
  "fisher": "RPL:1",
  "yates": "RPL:1",
  "shuffel": "RPL:1",
  "analytical": "RPL:1 KCV:1",
  "hierarchy": "RPL:1 KCV:1",
  "process": "RPL:1 KCV:1",
  "additive": "RPL:1 KCV:1",
  "weighting": "RPL:1 KCV:1",
  "k-means": "RPL:1 KCV:1",
  "kriptografi": "KBJ:1",
  "keamanan": "KBJ:1",
  "robotik": "KBJ:1",
  "mikrokontroler": "KBJ:1",
  "wireless": "KBJ:1",
  "gateway": "KBJ:1",
  "arduino": "KBJ:1",
  "protokol": "KBJ:1",
  "prototipe": "KBJ:1",
  "konversi": "KBJ:1",
  "bandwidth": "KBJ:1",
  "router": "KBJ:1",
  "transmisi": "KBJ:1",
  "paket": "KBJ:1",
  "klien": "KBJ:1",
  "service": "KBJ:2",
  "nirkabel": "KBJ:1",
  "cloud": "KBJ:1",
  "otomatisasi": "KBJ:1",
  "internet": "KBJ:1",
  "things": "KBJ:1",
  "iot": "KBJ:1",
  "mikrotik": "KBJ:1",
  "sms": "KBJ:1",
  "enkripsi": "KBJ:1",
  "private": "KBJ:1",
  "file": "KBJ:1",
  "url": "KBJ:1",
  "serang": "KBJ:1",
  "recording": "KBJ:1",
  "jaringan": "KBJ:1",
  "attack": "KBJ:1",
  "cegah": "KBJ:1",
  "dekripsi": "KBJ:1",
  "monitoring": "KBJ:1",
  "server": "KBJ:1",
  "client": "KBJ:1",
  "distribusi": "KBJ:1",
  "acsess": "KBJ:1",
  "point": "KBJ:1",
  "email": "KBJ:1",
  "konfigurasi": "KBJ:1",
  "port": "KBJ:1",
  "optimalisasi": "KBJ:1",
  "security": "KBJ:1",
  "wifi": "KBJ:1",
  "hotspot": "KBJ:1",
  "frekuensi": "KBJ:1",
  "ghz": "KBJ:1",
  "vector": "KCV:1",
  "space": "KCV:1",
  "model": "KCV:1",
  "citra": "KCV:1",
  "bm25": "KCV:1",
  "identifikasi": "KCV:1",
  "fuzzy": "KCV:1",
  "diagnosis": "KCV:1",
  "deteksi": "KCV:1",
  "logika": "KCV:2",
  "ekstraksi": "KCV:1",
  "pakar": "KCV:1",
  "genetika": "KCV:1",
  "visualisasi": "KCV:1",
  "virtual": "KCV:1",
  "chi": "KCV:1",
  "square": "KCV:1",
  "manhattan": "KCV:1",
  "matlab": "KCV:1",
  "neural": "KCV:1",
  "deep": "KCV:1",
  "finger": "KCV:1",
  "pengenalan": "KCV:1",
  "landmark": "KCV:1",
  "pola": "KCV:1",
  "saraf": "KCV:1",
  "learning": "KCV:1",
  "tsukamoto": "KCV:1",
  "mamdani": "KCV:1",
  "digital": "KCV:1",
  "wajah": "KCV:1",
  "retina": "KCV:1",
  "defuzzyfikasi": "KCV:1",
  "inference": "KCV:1",
  "watermarking": "KCV:1",
  "grayscale": "KCV:2",
  "pixel": "KCV:2",
  "kontras": "KCV:1",
  "distance": "KCV:1",
  "sugeno": "KCV:1",
  "eulidean": "KCV:1",
  "certainty": "KCV:1",
  "n-gram": "KCV:1",
  "k-gram": "KCV:1",
  "retrieval": "KCV:1",
  "histogram": "KCV:1",
  "wafelet": "KCV:1",
  "canny": "KCV:1",
  "viola": "KCV:1",
  "fuzzyfikasi": "KCV:1",
  "reducer": "KCV:1",
  "rules": "KCV:1",
  "filter": "KCV:1",
  "machine": "KCV:1",
  "crips": "KCV:1",
  "artificial": "KCV:1",
  "konvolusi": "KCV:1",
  "realtime": "KCV:1",
  "vsm": "KCV:1",
  "tf": "KCV:1",
  "idf": "KCV:1",
  "yolo": "KCV:1",
  "cnn": "KCV:1",
  "rcnn": "KCV:1",
  "convolusional": "KCV:1",
  "pca": "KCV:1",
  "tekstur": "KCV:1",
  "daubechies": "KCV:1",
  "cephalometry": "KCV:1",
  "radiografi": "KCV:1",
  "iris": "KCV:1",
  "scanner": "KCV:1",
  "sobel": "KCV:1"
}